src/pe.v
module PE #(
    parameter WIDTH = 8
)(
    input wire clk,
    input wire rst,
    input wire clear,
    input wire signed [WIDTH-1:0] a_in,
    input wire signed [WIDTH-1:0] b_in,

    output reg signed [WIDTH-1:0] a_out,
    output reg signed [WIDTH-1:0] b_out,
    output reg signed [WIDTH*2-1:0] c_out
);

    always @(posedge clk) begin
        if (rst) begin
            c_out <= 0;
            a_out <= 0;
            b_out <= 0;
        end else begin
            a_out <= a_in;
            b_out <= b_in;
            if (clear) begin
                c_out <= a_in * b_in;
            end else begin
                c_out <= c_out + (a_in * b_in);
            end
        end
    end

endmodule

src/systolic_array.v


module systolic_array #(
    parameter WIDTH = 8
)(
    input wire clk,
    input wire rst,
    input wire clear,
    input wire activation,

    input wire signed [WIDTH-1:0] a_data0,
    input wire signed [WIDTH-1:0] a_data1,
    input wire signed [WIDTH-1:0] b_data0,
    input wire signed [WIDTH-1:0] b_data1,

    output wire signed [WIDTH*2-1:0] c00,
    output wire signed [WIDTH*2-1:0] c01,
    output wire signed [WIDTH*2-1:0] c10,
    output wire signed [WIDTH*2-1:0] c11
);


    wire signed [WIDTH-1:0] a_wire [0:1][0:2];
    wire signed [WIDTH-1:0] b_wire [0:2][0:1];
    wire signed [WIDTH*2-1:0] c_array[0:1][0:1];

    assign a_wire[0][0] = a_data0;
    assign a_wire[1][0] = a_data1;
    assign b_wire[0][0] = b_data0;
    assign b_wire[0][1] = b_data1;

    genvar i,j;
    generate
        for (i=0;i<2;i =i +1)begin : row 
            for( j=0;j<2;j=j+1) begin : col
                PE #(.WIDTH(WIDTH)) pe_inst (
                    .clk(clk),
                    .rst(rst),
                    .clear(clear),
                    .a_in(a_wire[i][j]),
                    .b_in(b_wire[i][j]),
                    .a_out(a_wire[i][j+1]),
                    .b_out(b_wire[i+1][j]),
                    .c_out(c_array[i][j])
                );
            end
        end
    endgenerate


    // combinational logic for output with optional reLu

    assign c00 = activation ? (c_array[0][0] < 0 ? 0 : c_array[0][0]) : c_array[0][0];
    assign c01 = activation ? (c_array[0][1] < 0 ? 0 : c_array[0][1]) : c_array[0][1];
    assign c10 = activation ? (c_array[1][0] < 0 ? 0 : c_array[1][0]) : c_array[1][0];
    assign c11 = activation ? (c_array[1][1] < 0 ? 0 : c_array[1][1]) : c_array[1][1];

    endmodule

test/systolic_array/systolic_array_tb.v
`default_nettype none

`timescale 1ns/1ps

module systolic_array_tb;

    initial begin
`ifdef VCD_PATH
        $dumpfile(`VCD_PATH);
`else
        $dumpfile("systolic_array_tb.vcd");
`endif
        $dumpvars(0, systolic_array_tb);
        #1;
    end

    reg clk;
    reg rst;
    reg clear;
    reg activation;
    reg signed [7:0] a_data0;
    reg signed [7:0] a_data1;
    reg signed [7:0] b_data0;
    reg signed [7:0] b_data1;

    wire signed [15:0] c00;
    wire signed [15:0] c01;
    wire signed [15:0] c10;
    wire signed [15:0] c11;

    systolic_array #(.WIDTH(8)) dut(
        .clk(clk),
        .rst(rst),
        .clear(clear),
        .activation(activation),
        .a_data0(a_data0),
        .a_data1(a_data1),
        .b_data0(b_data0),
        .b_data1(b_data1),
        .c00(c00),
        .c01(c01),
        .c10(c10),
        .c11(c11)
    );

endmodule

test/systolic_array/wave/systolic_array_tb_20260417_081801.vcd
$date
	Fri Apr 17 17:48:01 2026
$end
$version
	Icarus Verilog
$end
$timescale
	1ps
$end
$scope module systolic_array_tb $end
$var wire 16 ! c11 [15:0] $end
$var wire 16 " c10 [15:0] $end
$var wire 16 # c01 [15:0] $end
$var wire 16 $ c00 [15:0] $end
$var reg 8 % a_data0 [7:0] $end
$var reg 8 & a_data1 [7:0] $end
$var reg 1 ' activation $end
$var reg 8 ( b_data0 [7:0] $end
$var reg 8 ) b_data1 [7:0] $end
$var reg 1 * clear $end
$var reg 1 + clk $end
$var reg 1 , rst $end
$scope module dut $end
$var wire 8 - a_data0 [7:0] $end
$var wire 8 . a_data1 [7:0] $end
$var wire 1 ' activation $end
$var wire 8 / b_data0 [7:0] $end
$var wire 8 0 b_data1 [7:0] $end
$var wire 1 * clear $end
$var wire 1 + clk $end
$var wire 1 , rst $end
$var wire 16 1 c11 [15:0] $end
$var wire 16 2 c10 [15:0] $end
$var wire 16 3 c01 [15:0] $end
$var wire 16 4 c00 [15:0] $end
$var parameter 32 5 WIDTH $end
$scope begin row[0] $end
$var parameter 2 6 i $end
$scope begin col[0] $end
$var parameter 2 7 j $end
$scope module pe_inst $end
$var wire 8 8 a_in [7:0] $end
$var wire 8 9 b_in [7:0] $end
$var wire 1 * clear $end
$var wire 1 + clk $end
$var wire 1 , rst $end
$var parameter 32 : WIDTH $end
$var reg 8 ; a_out [7:0] $end
$var reg 8 < b_out [7:0] $end
$var reg 16 = c_out [15:0] $end
$upscope $end
$upscope $end
$scope begin col[1] $end
$var parameter 2 > j $end
$scope module pe_inst $end
$var wire 8 ? a_in [7:0] $end
$var wire 8 @ b_in [7:0] $end
$var wire 1 * clear $end
$var wire 1 + clk $end
$var wire 1 , rst $end
$var parameter 32 A WIDTH $end
$var reg 8 B a_out [7:0] $end
$var reg 8 C b_out [7:0] $end
$var reg 16 D c_out [15:0] $end
$upscope $end
$upscope $end
$upscope $end
$scope begin row[1] $end
$var parameter 2 E i $end
$scope begin col[0] $end
$var parameter 2 F j $end
$scope module pe_inst $end
$var wire 8 G a_in [7:0] $end
$var wire 8 H b_in [7:0] $end
$var wire 1 * clear $end
$var wire 1 + clk $end
$var wire 1 , rst $end
$var parameter 32 I WIDTH $end
$var reg 8 J a_out [7:0] $end
$var reg 8 K b_out [7:0] $end
$var reg 16 L c_out [15:0] $end
$upscope $end
$upscope $end
$scope begin col[1] $end
$var parameter 2 M j $end
$scope module pe_inst $end
$var wire 8 N a_in [7:0] $end
$var wire 8 O b_in [7:0] $end
$var wire 1 * clear $end
$var wire 1 + clk $end
$var wire 1 , rst $end
$var parameter 32 P WIDTH $end
$var reg 8 Q a_out [7:0] $end
$var reg 8 R b_out [7:0] $end
$var reg 16 S c_out [15:0] $end
$upscope $end
$upscope $end
$upscope $end
$upscope $end
$upscope $end
$enddefinitions $end
$comment Show the parameter values. $end
$dumpall
b1000 P
b1 M
b1000 I
b0 F
b1 E
b1000 A
b1 >
b1000 :
b0 7
b0 6
b1000 5
$end
#0
$dumpvars
b0 S
b0 R
b0 Q
b0 O
b0 N
b0 L
b0 K
b0 J
b0 H
bz G
b0 D
b0 C
b0 B
b0 @
b0 ?
b0 =
b0 <
b0 ;
b0 9
b0 8
b0 4
b0 3
b0 2
b0 1
b0 0
b0 /
b0 .
b0 -
1,
1+
1*
b0 )
b0 (
0'
b0 &
b0 %
b0 $
b0 #
b0 "
b0 !
$end
#5000
0+
#10000
1+
#15000
0+
#20000
0*
bx "
bx 2
bx L
bz J
bz N
1+
0,
#25000
0+
#30000
b10 9
b10 (
b10 /
b1 8
b1 %
b1 -
bx !
bx 1
bx S
bz Q
1+
#35000
0+
#40000
b101 @
b101 )
b101 0
b11 9
b11 (
b11 /
b101 &
b101 .
b100 8
b100 %
b100 -
b10 $
b10 4
b10 =
b10 <
b10 H
b0x01 ?
b1 ;
1+
#45000
0+
#50000
b1001 @
b1001 )
b1001 0
b0 9
b0 (
b0 /
b1001 &
b1001 .
b0 8
b0 %
b0 -
bx #
bx 3
b1110 $
b1110 4
b10 K
bx D
b101 C
b101 O
b0x01 B
b1110 =
b11 <
b11 H
b0xx0x ?
b100 ;
1+
#55000
0+
#60000
b0 @
b0 )
b0 0
b0 &
b0 .
b0 <
b0 H
b0 ?
b0 ;
b1001 C
b1001 O
b0xx0x B
b11 K
b101 R
1+
#65000
0+
#70000
b1001 R
b0 K
b0 C
b0 O
b0 B
1+
#75000
0+
#80000
b0 R
1+
