src/control_unit.v


module control_unit (
    input wire clk,
    input wire rst,
    input wire load_en,


    // Memory interface connections
    output reg [2:0] mem_addr,

    // MMU interface connections
    output reg [2:0] mmu_cycle,
    output reg mmu_en,

    // for debugging
    output wire [1:0] state_out
);


    localparam [1:0] S_IDLE                     = 2'b00;
    localparam [1:0] S_LOAD_MATS                = 2'b01;
    localparam [1:0] S_MMU_FEED_COMPUTE_WB      = 2'b10;

    reg [1:0] state, next_state;

    assign state_out = state;

    always @(*) begin
        next_state = state;

        case(state) 
            S_IDLE: begin
                if (load_en) begin
                    next_state = S_LOAD_MATS;
                end
            end

            S_LOAD_MATS: begin
                
                if (mem_addr == 3'b111) begin
                    next_state = S_MMU_FEED_COMPUTE_WB;
                end
            end 

            S_MMU_FEED_COMPUTE_WB:
                next_state = S_MMU_FEED_COMPUTE_WB;



            default: begin
                next_state = S_IDLE;

            end
        endcase
    end


    // STATE MACHINE
    always @(posedge clk) begin
        if (rst) begin
            state <= S_IDLE;
            mmu_cycle <= 0;
            mmu_en <= 0;
            mem_addr <=0;
        end else begin 
            state <= next_state;
            mem_addr <=0;
            case (state)
                S_IDLE : begin
                    mmu_cycle <= 0;
                    mmu_en <= 0;
                    if (load_en) begin
                        mem_addr <= mem_addr + 1;
                    end
                end

                S_LOAD_MATS: begin
                    if (load_en) begin
                        mem_addr <= mem_addr + 1;
                    end

                    if (mem_addr == 3'b101) begin
                        mmu_en <= 1;
                    end else if (mem_addr >= 3'b110) begin
                        mmu_en <= 1;
                        mmu_cycle <= mmu_cycle + 1;
                        if (mem_addr == 3'b111) begin
                            mem_addr <= 0;
                        end
                    end
                end

                S_MMU_FEED_COMPUTE_WB : begin
                    if (load_en) begin
                        mem_addr <= mem_addr + 1;
                    end
                    mmu_cycle <= mmu_cycle + 1;

                    if (mmu_cycle == 3'b111) begin
                        mmu_cycle <= 0;
                    end else if (mmu_cycle == 1) begin
                        mem_addr <= 0;
                    end
                end

                default : begin
                    mmu_cycle <= 0;
                    mmu_en <= 0;
                end
            endcase
        end
    end

endmodule

test/control_unit/control_unit_tb.v

`default_nettype none
`timescale 1ns/1ps


module control_unit_tb();

    initial begin
`ifdef VCD_PATH
        $dumpfile(`VCD_PATH);
`else 
        $dumpfile("control_unit.vcd");
`endif 
        $dumpvars(0, control_unit_tb);
        #1;
    end


    reg clk;
    reg rst;
    reg load_en;
    wire [1:0] state_out;

    wire [2:0] mem_addr;
    wire mmu_en;
    wire [2:0] mmu_cycle;

    control_unit dut(
        .clk(clk),
        .rst(rst),
        .load_en(load_en),
        .mem_addr(mem_addr),
        .mmu_en(mmu_en),
        .mmu_cycle(mmu_cycle),
        .state_out(state_out)
    );


endmodule

test/control_unit/wave/control_unit_tb_20260512_132954.vcd
$date
	Tue May 12 22:59:55 2026
$end
$version
	Icarus Verilog
$end
$timescale
	1ps
$end
$scope module control_unit_tb $end
$var wire 2 ! state_out [1:0] $end
$var wire 1 " mmu_en $end
$var wire 3 # mmu_cycle [2:0] $end
$var wire 3 $ mem_addr [2:0] $end
$var reg 1 % clk $end
$var reg 1 & load_en $end
$var reg 1 ' rst $end
$scope module dut $end
$var wire 1 % clk $end
$var wire 1 & load_en $end
$var wire 1 ' rst $end
$var wire 2 ( state_out [1:0] $end
$var parameter 2 ) S_IDLE $end
$var parameter 2 * S_LOAD_MATS $end
$var parameter 2 + S_MMU_FEED_COMPUTE_WB $end
$var reg 3 , mem_addr [2:0] $end
$var reg 3 - mmu_cycle [2:0] $end
$var reg 1 " mmu_en $end
$var reg 2 . next_state [1:0] $end
$var reg 2 / state [1:0] $end
$upscope $end
$upscope $end
$enddefinitions $end
$comment Show the parameter values. $end
$dumpall
b10 +
b1 *
b0 )
$end
#0
$dumpvars
b0 /
b0 .
b0 -
b0 ,
b0 (
1'
0&
1%
b0 $
b0 #
0"
b0 !
$end
#10000
0%
#20000
0'
1%
#30000
0%
#40000
1%
#40001
1'
#50001
0%
#60001
1%
#70001
0%
#80001
0'
1%
#90001
0%
#100001
1%
#110001
0%
#120001
1%
#130001
0%
#140001
1%
#150001
0%
#160001
1%
#170001
0%
#180001
1%
#190001
0%
#200001
1%
#200002
1'
#210002
0%
#220002
1%
#230002
0%
#240002
0'
1%
#250002
0%
#260002
b1 .
1&
1%
#270002
0%
#280002
b1 $
b1 ,
b1 !
b1 (
b1 /
1%
#290002
0%
#300002
b10 $
b10 ,
1%
#310002
0%
#320002
b11 $
b11 ,
1%
#330002
0%
#340002
b100 $
b100 ,
1%
#350002
0%
#360002
b101 $
b101 ,
1%
#370002
0%
#380002
1"
b110 $
b110 ,
1%
#390002
0%
#400002
b10 .
b1 #
b1 -
b111 $
b111 ,
1%
#410002
0%
#420002
b10 #
b10 -
b0 $
b0 ,
b10 !
b10 (
b10 /
1%
#430002
0%
#440002
0&
b11 #
b11 -
b1 $
b1 ,
1%
#440003
1'
#450003
0%
#460003
b0 .
b0 $
b0 ,
0"
b0 #
b0 -
b0 !
b0 (
b0 /
1%
#470003
0%
#480003
0'
1%
#490003
0%
#500003
b1 .
1&
1%
#510003
0%
#520003
b1 $
b1 ,
b1 !
b1 (
b1 /
1%
#530003
0%
#540003
b10 $
b10 ,
1%
#550003
0%
#560003
b11 $
b11 ,
1%
#570003
0%
#580003
b100 $
b100 ,
1%
#590003
0%
#600003
b101 $
b101 ,
1%
#610003
0%
#620003
1"
b110 $
b110 ,
1%
#630003
0%
#640003
b10 .
b1 #
b1 -
b111 $
b111 ,
1%
#650003
0%
#660003
0&
b10 #
b10 -
b0 $
b0 ,
b10 !
b10 (
b10 /
1%
#670003
0%
#680003
b11 #
b11 -
1%
#690003
0%
#700003
b100 #
b100 -
1%
#710003
0%
#720003
b101 #
b101 -
1%
#730003
0%
#740003
b110 #
b110 -
1%
#750003
0%
#760003
b111 #
b111 -
1%
#770003
0%
#780003
b0 #
b0 -
1%
#790003
0%
#800003
b1 #
b1 -
1%
#810003
0%
#820003
b10 #
b10 -
1%
#820004
1'
#830004
0%
#840004
b0 .
0"
b0 #
b0 -
b0 !
b0 (
b0 /
1%
#850004
0%
#860004
0'
1%
#870004
0%
#880004
b1 .
1&
1%
#890004
0%
#900004
b1 $
b1 ,
b1 !
b1 (
b1 /
1%
#910004
0%
#920004
b10 $
b10 ,
1%
#930004
0%
#940004
b11 $
b11 ,
1%
#950004
0%
#960004
b100 $
b100 ,
1%
#970004
0%
#980004
b101 $
b101 ,
1%
#990004
0%
#1000004
1"
b110 $
b110 ,
1%
#1010004
0%
#1020004
b10 .
b1 #
b1 -
b111 $
b111 ,
1%
#1030004
0%
#1040004
b10 #
b10 -
b0 $
b0 ,
b10 !
b10 (
b10 /
1%
#1050004
0%
#1060004
b11 #
b11 -
b1 $
b1 ,
1%
#1070004
0%
#1080004
b100 #
b100 -
b10 $
b10 ,
1%
#1090004
0%
#1100004
b101 #
b101 -
b11 $
b11 ,
1%
#1110004
0%
#1120004
b110 #
b110 -
b100 $
b100 ,
1%
#1130004
0%
#1140004
b111 #
b111 -
b101 $
b101 ,
1%
#1150004
0%
#1160004
b0 #
b0 -
b110 $
b110 ,
1%
#1170004
0%
#1180004
b1 #
b1 -
b111 $
b111 ,
1%
#1180005
0&
1'
#1190005
0%
#1200005
b0 .
b0 $
b0 ,
0"
b0 #
b0 -
b0 !
b0 (
b0 /
1%
#1210005
0%
#1220005
0'
1%
#1230005
0%
#1240005
b1 .
1&
1%
#1250005
0%
#1260005
b1 $
b1 ,
b1 !
b1 (
b1 /
1%
#1270005
0%
#1280005
b10 $
b10 ,
1%
#1290005
0%
#1300005
b11 $
b11 ,
1%
#1310005
0%
#1320005
b100 $
b100 ,
1%
#1330005
0%
#1340005
b101 $
b101 ,
1%
#1350005
0%
#1360005
1"
b110 $
b110 ,
1%
#1370005
0%
#1380005
b10 .
b1 #
b1 -
b111 $
b111 ,
1%
#1390005
0%
#1400005
b10 #
b10 -
b0 $
b0 ,
b10 !
b10 (
b10 /
1%
#1410005
0%
#1420005
0&
b11 #
b11 -
b1 $
b1 ,
1%
#1430005
0%
#1440005
1&
b100 #
b100 -
b0 $
b0 ,
1%
#1450005
0%
#1460005
0&
b101 #
b101 -
b1 $
b1 ,
1%
#1470005
0%
#1480005
1&
b110 #
b110 -
b0 $
b0 ,
1%
#1490005
0%
#1500005
0&
b111 #
b111 -
b1 $
b1 ,
1%
#1510005
0%
#1520005
b0 #
b0 -
b0 $
b0 ,
1%
#1520006
1'
#1530006
0%
#1540006
b0 .
0"
b0 !
b0 (
b0 /
1%
#1550006
0%
#1560006
0'
1%
#1570006
0%
#1580006
b1 .
1&
1%
#1590006
0%
#1600006
b1 $
b1 ,
b1 !
b1 (
b1 /
1%
#1610006
0%
#1620006
b10 $
b10 ,
1%
#1630006
0%
#1640006
b11 $
b11 ,
1%
#1650006
0%
#1660006
b100 $
b100 ,
1%
#1670006
0%
#1680006
b101 $
b101 ,
1%
#1690006
0%
#1700006
1"
b110 $
b110 ,
1%
#1710006
0%
#1720006
b10 .
b1 #
b1 -
b111 $
b111 ,
1%
#1730006
0%
#1740006
b10 #
b10 -
b0 $
b0 ,
b10 !
b10 (
b10 /
1%
#1750006
0%
#1760006
b11 #
b11 -
b1 $
b1 ,
1%
#1770006
0%
#1780006
b100 #
b100 -
b10 $
b10 ,
1%
#1790006
0%
#1800006
b101 #
b101 -
b11 $
b11 ,
1%
#1810006
0%
#1820006
b110 #
b110 -
b100 $
b100 ,
1%
#1830006
0%
#1840006
b111 #
b111 -
b101 $
b101 ,
1%
#1850006
0%
#1860006
b0 #
b0 -
b110 $
b110 ,
1%
#1870006
0%
#1880006
b1 #
b1 -
b111 $
b111 ,
1%
#1890006
0%
#1900006
0&
b10 #
b10 -
b0 $
b0 ,
1%
#1910006
0%
#1920006
b11 #
b11 -
1%
#1930006
0%
#1940006
b100 #
b100 -
1%
#1950006
0%
#1960006
b101 #
b101 -
1%
#1970006
0%
#1980006
b110 #
b110 -
1%
#1990006
0%
#2000006
b111 #
b111 -
1%
#2010006
0%
#2020006
b0 #
b0 -
1%
#2030006
0%
#2040006
b1 #
b1 -
1%
#2050006
0%
#2060006
b10 #
b10 -
1%
#2070006
0%
#2080006
b11 #
b11 -
1%
#2090006
0%
#2100006
b100 #
b100 -
1%
#2110006
0%
#2120006
b101 #
b101 -
1%
#2130006
0%
#2140006
b110 #
b110 -
1%
#2150006
0%
#2160006
b111 #
b111 -
1%
#2170006
0%
#2180006
b0 #
b0 -
1%
#2190006
0%
#2200006
b1 #
b1 -
1%
#2210006
0%
#2220006
b10 #
b10 -
1%
#2230006
0%
#2240006
b11 #
b11 -
1%
#2250006
0%
#2260006
b100 #
b100 -
1%
#2270006
0%
#2280006
b101 #
b101 -
1%
#2290006
0%
#2300006
b110 #
b110 -
1%
#2310006
0%
#2320006
b111 #
b111 -
1%
#2330006
0%
#2340006
b0 #
b0 -
1%
#2350006
0%
#2360006
b1 #
b1 -
1%
#2370006
0%
#2380006
b10 #
b10 -
1%
#2390006
0%
#2400006
b11 #
b11 -
1%
#2410006
0%
#2420006
b100 #
b100 -
1%
#2430006
0%
#2440006
b101 #
b101 -
1%
#2450006
0%
#2460006
b110 #
b110 -
1%
#2470006
0%
#2480006
b111 #
b111 -
1%
#2490006
0%
#2500006
b0 #
b0 -
1%
#2510006
0%
#2520006
b1 #
b1 -
1%
#2530006
0%
#2540006
b10 #
b10 -
1%
#2550006
0%
#2560006
b11 #
b11 -
1%
#2570006
0%
#2580006
b100 #
b100 -
1%
#2590006
0%
#2600006
b101 #
b101 -
1%
#2610006
0%
#2620006
b110 #
b110 -
1%
#2630006
0%
#2640006
b111 #
b111 -
1%
#2650006
0%
#2660006
b0 #
b0 -
1%
#2670006
0%
#2680006
b1 #
b1 -
1%
#2690006
0%
#2700006
b10 #
b10 -
1%
#2710006
0%
#2720006
b11 #
b11 -
1%
#2730006
0%
#2740006
b100 #
b100 -
1%
#2750006
0%
#2760006
b101 #
b101 -
1%
#2770006
0%
#2780006
b110 #
b110 -
1%
#2790006
0%
#2800006
b111 #
b111 -
1%
#2810006
0%
#2820006
b0 #
b0 -
1%
#2830006
0%
#2840006
b1 #
b1 -
1%
#2850006
0%
#2860006
b10 #
b10 -
1%
#2870006
0%
#2880006
b11 #
b11 -
1%
#2890006
0%
#2900006
b100 #
b100 -
1%
#2910006
0%
#2920006
b101 #
b101 -
1%
#2930006
0%
#2940006
b110 #
b110 -
1%
#2950006
0%
#2960006
b111 #
b111 -
1%
#2970006
0%
#2980006
b0 #
b0 -
1%
#2990006
0%
#3000006
b1 #
b1 -
1%
#3010006
0%
#3020006
b10 #
b10 -
1%
#3030006
0%
#3040006
b11 #
b11 -
1%
#3050006
0%
#3060006
b100 #
b100 -
1%
#3070006
0%
#3080006
b101 #
b101 -
1%
#3090006
0%
#3100006
b110 #
b110 -
1%
#3110006
0%
#3120006
b111 #
b111 -
1%
#3130006
0%
#3140006
b0 #
b0 -
1%
#3150006
0%
#3160006
b1 #
b1 -
1%
#3170006
0%
#3180006
b10 #
b10 -
1%
#3190006
0%
#3200006
b11 #
b11 -
1%
#3210006
0%
#3220006
b100 #
b100 -
1%
#3230006
0%
#3240006
b101 #
b101 -
1%
#3250006
0%
#3260006
b110 #
b110 -
1%
#3270006
0%
#3280006
b111 #
b111 -
1%
#3290006
0%
#3300006
b0 #
b0 -
1%
#3310006
0%
#3320006
b1 #
b1 -
1%
#3330006
0%
#3340006
b10 #
b10 -
1%
#3350006
0%
#3360006
b11 #
b11 -
1%
#3370006
0%
#3380006
b100 #
b100 -
1%
#3390006
0%
#3400006
b101 #
b101 -
1%
#3410006
0%
#3420006
b110 #
b110 -
1%
#3430006
0%
#3440006
b111 #
b111 -
1%
#3450006
0%
#3460006
b0 #
b0 -
1%
#3470006
0%
#3480006
b1 #
b1 -
1%
#3490006
0%
#3500006
b10 #
b10 -
1%
#3510006
0%
#3520006
b11 #
b11 -
1%
#3530006
0%
#3540006
b100 #
b100 -
1%
#3550006
0%
#3560006
b101 #
b101 -
1%
#3570006
0%
#3580006
b110 #
b110 -
1%
#3590006
0%
#3600006
b111 #
b111 -
1%
#3610006
0%
#3620006
b0 #
b0 -
1%
#3630006
0%
#3640006
b1 #
b1 -
1%
#3650006
0%
#3660006
b10 #
b10 -
1%
#3670006
0%
#3680006
b11 #
b11 -
1%
#3690006
0%
#3700006
b100 #
b100 -
1%
#3710006
0%
#3720006
b101 #
b101 -
1%
#3730006
0%
#3740006
b110 #
b110 -
1%
#3750006
0%
#3760006
b111 #
b111 -
1%
#3770006
0%
#3780006
b0 #
b0 -
1%
#3790006
0%
#3800006
b1 #
b1 -
1%
#3810006
0%
#3820006
b10 #
b10 -
1%
#3830006
0%
#3840006
b11 #
b11 -
1%
#3850006
0%
#3860006
b100 #
b100 -
1%
#3870006
0%
#3880006
b101 #
b101 -
1%
#3890006
0%
#3900006
b110 #
b110 -
1%
#3910006
0%
#3920006
b111 #
b111 -
1%
#3930006
0%
#3940006
b0 #
b0 -
1%
#3950006
0%
#3960006
b1 #
b1 -
1%
#3970006
0%
#3980006
b10 #
b10 -
1%
#3990006
0%
#4000006
b11 #
b11 -
1%
#4010006
0%
#4020006
b100 #
b100 -
1%
#4030006
0%
#4040006
b101 #
b101 -
1%
#4050006
0%
#4060006
b110 #
b110 -
1%
#4070006
0%
#4080006
b111 #
b111 -
1%
#4090006
0%
#4100006
b0 #
b0 -
1%
#4110006
0%
#4120006
b1 #
b1 -
1%
#4130006
0%
#4140006
b10 #
b10 -
1%
#4150006
0%
#4160006
b11 #
b11 -
1%
#4170006
0%
#4180006
b100 #
b100 -
1%
#4190006
0%
#4200006
b101 #
b101 -
1%
#4210006
0%
#4220006
b110 #
b110 -
1%
#4230006
0%
#4240006
b111 #
b111 -
1%
#4250006
0%
#4260006
b0 #
b0 -
1%
#4270006
0%
#4280006
b1 #
b1 -
1%
#4290006
0%
#4300006
b10 #
b10 -
1%
#4310006
0%
#4320006
b11 #
b11 -
1%
#4330006
0%
#4340006
b100 #
b100 -
1%
#4350006
0%
#4360006
b101 #
b101 -
1%
#4370006
0%
#4380006
b110 #
b110 -
1%
#4390006
0%
#4400006
b111 #
b111 -
1%
#4410006
0%
#4420006
b0 #
b0 -
1%
#4430006
0%
#4440006
b1 #
b1 -
1%
#4450006
0%
#4460006
b10 #
b10 -
1%
#4470006
0%
#4480006
b11 #
b11 -
1%
#4490006
0%
#4500006
b100 #
b100 -
1%
#4510006
0%
#4520006
b101 #
b101 -
1%
#4530006
0%
#4540006
b110 #
b110 -
1%
#4550006
0%
#4560006
b111 #
b111 -
1%
#4570006
0%
#4580006
b0 #
b0 -
1%
#4590006
0%
#4600006
b1 #
b1 -
1%
#4610006
0%
#4620006
b10 #
b10 -
1%
#4630006
0%
#4640006
b11 #
b11 -
1%
#4650006
0%
#4660006
b100 #
b100 -
1%
#4670006
0%
#4680006
b101 #
b101 -
1%
#4690006
0%
#4700006
b110 #
b110 -
1%
#4710006
0%
#4720006
b111 #
b111 -
1%
#4730006
0%
#4740006
b0 #
b0 -
1%
#4750006
0%
#4760006
b1 #
b1 -
1%
#4770006
0%
#4780006
b10 #
b10 -
1%
#4790006
0%
#4800006
b11 #
b11 -
1%
#4810006
0%
#4820006
b100 #
b100 -
1%
#4830006
0%
#4840006
b101 #
b101 -
1%
#4850006
0%
#4860006
b110 #
b110 -
1%
#4870006
0%
#4880006
b111 #
b111 -
1%
#4890006
0%
#4900006
b0 #
b0 -
1%
#4910006
0%
#4920006
b1 #
b1 -
1%
#4930006
0%
#4940006
b10 #
b10 -
1%
#4950006
0%
#4960006
b11 #
b11 -
1%
#4970006
0%
#4980006
b100 #
b100 -
1%
#4990006
0%
#5000006
b101 #
b101 -
1%
#5010006
0%
#5020006
b110 #
b110 -
1%
#5030006
0%
#5040006
b111 #
b111 -
1%
#5050006
0%
#5060006
b0 #
b0 -
1%
#5070006
0%
#5080006
b1 #
b1 -
1%
#5090006
0%
#5100006
b10 #
b10 -
1%
#5110006
0%
#5120006
b11 #
b11 -
1%
#5130006
0%
#5140006
b100 #
b100 -
1%
#5150006
0%
#5160006
b101 #
b101 -
1%
#5170006
0%
#5180006
b110 #
b110 -
1%
#5190006
0%
#5200006
b111 #
b111 -
1%
#5210006
0%
#5220006
b0 #
b0 -
1%
#5230006
0%
#5240006
b1 #
b1 -
1%
#5250006
0%
#5260006
b10 #
b10 -
1%
#5270006
0%
#5280006
b11 #
b11 -
1%
#5290006
0%
#5300006
b100 #
b100 -
1%
#5310006
0%
#5320006
b101 #
b101 -
1%
#5330006
0%
#5340006
b110 #
b110 -
1%
#5350006
0%
#5360006
b111 #
b111 -
1%
#5370006
0%
#5380006
b0 #
b0 -
1%
#5390006
0%
#5400006
b1 #
b1 -
1%
#5410006
0%
#5420006
b10 #
b10 -
1%
#5430006
0%
#5440006
b11 #
b11 -
1%
#5450006
0%
#5460006
b100 #
b100 -
1%
#5470006
0%
#5480006
b101 #
b101 -
1%
#5490006
0%
#5500006
b110 #
b110 -
1%
#5510006
0%
#5520006
b111 #
b111 -
1%
#5530006
0%
#5540006
b0 #
b0 -
1%
#5550006
0%
#5560006
b1 #
b1 -
1%
#5570006
0%
#5580006
b10 #
b10 -
1%
#5590006
0%
#5600006
b11 #
b11 -
1%
#5610006
0%
#5620006
b100 #
b100 -
1%
#5630006
0%
#5640006
b101 #
b101 -
1%
#5650006
0%
#5660006
b110 #
b110 -
1%
#5670006
0%
#5680006
b111 #
b111 -
1%
#5690006
0%
#5700006
b0 #
b0 -
1%
#5710006
0%
#5720006
b1 #
b1 -
1%
#5730006
0%
#5740006
b10 #
b10 -
1%
#5750006
0%
#5760006
b11 #
b11 -
1%
#5770006
0%
#5780006
b100 #
b100 -
1%
#5790006
0%
#5800006
b101 #
b101 -
1%
#5810006
0%
#5820006
b110 #
b110 -
1%
#5830006
0%
#5840006
b111 #
b111 -
1%
#5850006
0%
#5860006
b0 #
b0 -
1%
#5870006
0%
#5880006
b1 #
b1 -
1%
#5890006
0%
#5900006
b10 #
b10 -
1%
#5910006
0%
#5920006
b11 #
b11 -
1%
#5930006
0%
#5940006
b100 #
b100 -
1%
#5950006
0%
#5960006
b101 #
b101 -
1%
#5970006
0%
#5980006
b110 #
b110 -
1%
#5990006
0%
#6000006
b111 #
b111 -
1%
#6010006
0%
#6020006
b0 #
b0 -
1%
#6030006
0%
#6040006
b1 #
b1 -
1%
#6050006
0%
#6060006
b10 #
b10 -
1%
#6070006
0%
#6080006
b11 #
b11 -
1%
#6090006
0%
#6100006
b100 #
b100 -
1%
#6110006
0%
#6120006
b101 #
b101 -
1%
#6130006
0%
#6140006
b110 #
b110 -
1%
#6150006
0%
#6160006
b111 #
b111 -
1%
#6170006
0%
#6180006
b0 #
b0 -
1%
#6190006
0%
#6200006
b1 #
b1 -
1%
#6210006
0%
#6220006
b10 #
b10 -
1%
#6230006
0%
#6240006
b11 #
b11 -
1%
#6250006
0%
#6260006
b100 #
b100 -
1%
#6270006
0%
#6280006
b101 #
b101 -
1%
#6290006
0%
#6300006
b110 #
b110 -
1%
#6310006
0%
#6320006
b111 #
b111 -
1%
#6330006
0%
#6340006
b0 #
b0 -
1%
#6350006
0%
#6360006
b1 #
b1 -
1%
#6370006
0%
#6380006
b10 #
b10 -
1%
#6390006
0%
#6400006
b11 #
b11 -
1%
#6410006
0%
#6420006
b100 #
b100 -
1%
#6430006
0%
#6440006
b101 #
b101 -
1%
#6450006
0%
#6460006
b110 #
b110 -
1%
#6470006
0%
#6480006
b111 #
b111 -
1%
#6490006
0%
#6500006
b0 #
b0 -
1%
#6510006
0%
#6520006
b1 #
b1 -
1%
#6530006
0%
#6540006
b10 #
b10 -
1%
#6550006
0%
#6560006
b11 #
b11 -
1%
#6570006
0%
#6580006
b100 #
b100 -
1%
#6590006
0%
#6600006
b101 #
b101 -
1%
#6610006
0%
#6620006
b110 #
b110 -
1%
#6630006
0%
#6640006
b111 #
b111 -
1%
#6650006
0%
#6660006
b0 #
b0 -
1%
#6670006
0%
#6680006
b1 #
b1 -
1%
#6690006
0%
#6700006
b10 #
b10 -
1%
#6710006
0%
#6720006
b11 #
b11 -
1%
#6730006
0%
#6740006
b100 #
b100 -
1%
#6750006
0%
#6760006
b101 #
b101 -
1%
#6770006
0%
#6780006
b110 #
b110 -
1%
#6790006
0%
#6800006
b111 #
b111 -
1%
#6810006
0%
#6820006
b0 #
b0 -
1%
#6830006
0%
#6840006
b1 #
b1 -
1%
#6850006
0%
#6860006
b10 #
b10 -
1%
#6870006
0%
#6880006
b11 #
b11 -
1%
#6890006
0%
#6900006
b100 #
b100 -
1%
#6910006
0%
#6920006
b101 #
b101 -
1%
#6930006
0%
#6940006
b110 #
b110 -
1%
#6950006
0%
#6960006
b111 #
b111 -
1%
#6970006
0%
#6980006
b0 #
b0 -
1%
#6990006
0%
#7000006
b1 #
b1 -
1%
#7010006
0%
#7020006
b10 #
b10 -
1%
#7030006
0%
#7040006
b11 #
b11 -
1%
#7050006
0%
#7060006
b100 #
b100 -
1%
#7070006
0%
#7080006
b101 #
b101 -
1%
#7090006
0%
#7100006
b110 #
b110 -
1%
#7110006
0%
#7120006
b111 #
b111 -
1%
#7130006
0%
#7140006
b0 #
b0 -
1%
#7150006
0%
#7160006
b1 #
b1 -
1%
#7170006
0%
#7180006
b10 #
b10 -
1%
#7190006
0%
#7200006
b11 #
b11 -
1%
#7210006
0%
#7220006
b100 #
b100 -
1%
#7230006
0%
#7240006
b101 #
b101 -
1%
#7250006
0%
#7260006
b110 #
b110 -
1%
#7270006
0%
#7280006
b111 #
b111 -
1%
#7290006
0%
#7300006
b0 #
b0 -
1%
#7310006
0%
#7320006
b1 #
b1 -
1%
#7330006
0%
#7340006
b10 #
b10 -
1%
#7350006
0%
#7360006
b11 #
b11 -
1%
#7370006
0%
#7380006
b100 #
b100 -
1%
#7390006
0%
#7400006
b101 #
b101 -
1%
#7410006
0%
#7420006
b110 #
b110 -
1%
#7430006
0%
#7440006
b111 #
b111 -
1%
#7450006
0%
#7460006
b0 #
b0 -
1%
#7470006
0%
#7480006
b1 #
b1 -
1%
#7490006
0%
#7500006
b10 #
b10 -
1%
#7510006
0%
#7520006
b11 #
b11 -
1%
#7530006
0%
#7540006
b100 #
b100 -
1%
#7550006
0%
#7560006
b101 #
b101 -
1%
#7570006
0%
#7580006
b110 #
b110 -
1%
#7590006
0%
#7600006
b111 #
b111 -
1%
#7610006
0%
#7620006
b0 #
b0 -
1%
#7630006
0%
#7640006
b1 #
b1 -
1%
#7650006
0%
#7660006
b10 #
b10 -
1%
#7670006
0%
#7680006
b11 #
b11 -
1%
#7690006
0%
#7700006
b100 #
b100 -
1%
#7710006
0%
#7720006
b101 #
b101 -
1%
#7730006
0%
#7740006
b110 #
b110 -
1%
#7750006
0%
#7760006
b111 #
b111 -
1%
#7770006
0%
#7780006
b0 #
b0 -
1%
#7790006
0%
#7800006
b1 #
b1 -
1%
#7810006
0%
#7820006
b10 #
b10 -
1%
#7830006
0%
#7840006
b11 #
b11 -
1%
#7850006
0%
#7860006
b100 #
b100 -
1%
#7870006
0%
#7880006
b101 #
b101 -
1%
#7890006
0%
#7900006
b110 #
b110 -
1%
#7910006
0%
#7920006
b111 #
b111 -
1%
#7930006
0%
#7940006
b0 #
b0 -
1%
#7950006
0%
#7960006
b1 #
b1 -
1%
#7970006
0%
#7980006
b10 #
b10 -
1%
#7990006
0%
#8000006
b11 #
b11 -
1%
#8010006
0%
#8020006
b100 #
b100 -
1%
#8030006
0%
#8040006
b101 #
b101 -
1%
#8050006
0%
#8060006
b110 #
b110 -
1%
#8070006
0%
#8080006
b111 #
b111 -
1%
#8090006
0%
#8100006
b0 #
b0 -
1%
#8110006
0%
#8120006
b1 #
b1 -
1%
#8130006
0%
#8140006
b10 #
b10 -
1%
#8150006
0%
#8160006
b11 #
b11 -
1%
#8170006
0%
#8180006
b100 #
b100 -
1%
#8190006
0%
#8200006
b101 #
b101 -
1%
#8210006
0%
#8220006
b110 #
b110 -
1%
#8230006
0%
#8240006
b111 #
b111 -
1%
#8250006
0%
#8260006
b0 #
b0 -
1%
#8270006
0%
#8280006
b1 #
b1 -
1%
#8290006
0%
#8300006
b10 #
b10 -
1%
#8310006
0%
#8320006
b11 #
b11 -
1%
#8330006
0%
#8340006
b100 #
b100 -
1%
#8350006
0%
#8360006
b101 #
b101 -
1%
#8370006
0%
#8380006
b110 #
b110 -
1%
#8390006
0%
#8400006
b111 #
b111 -
1%
#8410006
0%
#8420006
b0 #
b0 -
1%
#8430006
0%
#8440006
b1 #
b1 -
1%
#8450006
0%
#8460006
b10 #
b10 -
1%
#8470006
0%
#8480006
b11 #
b11 -
1%
#8490006
0%
#8500006
b100 #
b100 -
1%
#8510006
0%
#8520006
b101 #
b101 -
1%
#8530006
0%
#8540006
b110 #
b110 -
1%
#8550006
0%
#8560006
b111 #
b111 -
1%
#8570006
0%
#8580006
b0 #
b0 -
1%
#8590006
0%
#8600006
b1 #
b1 -
1%
#8610006
0%
#8620006
b10 #
b10 -
1%
#8630006
0%
#8640006
b11 #
b11 -
1%
#8650006
0%
#8660006
b100 #
b100 -
1%
#8670006
0%
#8680006
b101 #
b101 -
1%
#8690006
0%
#8700006
b110 #
b110 -
1%
#8710006
0%
#8720006
b111 #
b111 -
1%
#8730006
0%
#8740006
b0 #
b0 -
1%
#8750006
0%
#8760006
b1 #
b1 -
1%
#8770006
0%
#8780006
b10 #
b10 -
1%
#8790006
0%
#8800006
b11 #
b11 -
1%
#8810006
0%
#8820006
b100 #
b100 -
1%
#8830006
0%
#8840006
b101 #
b101 -
1%
#8850006
0%
#8860006
b110 #
b110 -
1%
#8870006
0%
#8880006
b111 #
b111 -
1%
#8890006
0%
#8900006
b0 #
b0 -
1%
#8910006
0%
#8920006
b1 #
b1 -
1%
#8930006
0%
#8940006
b10 #
b10 -
1%
#8950006
0%
#8960006
b11 #
b11 -
1%
#8970006
0%
#8980006
b100 #
b100 -
1%
#8990006
0%
#9000006
b101 #
b101 -
1%
#9010006
0%
#9020006
b110 #
b110 -
1%
#9030006
0%
#9040006
b111 #
b111 -
1%
#9050006
0%
#9060006
b0 #
b0 -
1%
#9070006
0%
#9080006
b1 #
b1 -
1%
#9090006
0%
#9100006
b10 #
b10 -
1%
#9110006
0%
#9120006
b11 #
b11 -
1%
#9130006
0%
#9140006
b100 #
b100 -
1%
#9150006
0%
#9160006
b101 #
b101 -
1%
#9170006
0%
#9180006
b110 #
b110 -
1%
#9190006
0%
#9200006
b111 #
b111 -
1%
#9210006
0%
#9220006
b0 #
b0 -
1%
#9230006
0%
#9240006
b1 #
b1 -
1%
#9250006
0%
#9260006
b10 #
b10 -
1%
#9270006
0%
#9280006
b11 #
b11 -
1%
#9290006
0%
#9300006
b100 #
b100 -
1%
#9310006
0%
#9320006
b101 #
b101 -
1%
#9330006
0%
#9340006
b110 #
b110 -
1%
#9350006
0%
#9360006
b111 #
b111 -
1%
#9370006
0%
#9380006
b0 #
b0 -
1%
#9390006
0%
#9400006
b1 #
b1 -
1%
#9410006
0%
#9420006
b10 #
b10 -
1%
#9430006
0%
#9440006
b11 #
b11 -
1%
#9450006
0%
#9460006
b100 #
b100 -
1%
#9470006
0%
#9480006
b101 #
b101 -
1%
#9490006
0%
#9500006
b110 #
b110 -
1%
#9510006
0%
#9520006
b111 #
b111 -
1%
#9530006
0%
#9540006
b0 #
b0 -
1%
#9550006
0%
#9560006
b1 #
b1 -
1%
#9570006
0%
#9580006
b10 #
b10 -
1%
#9590006
0%
#9600006
b11 #
b11 -
1%
#9610006
0%
#9620006
b100 #
b100 -
1%
#9630006
0%
#9640006
b101 #
b101 -
1%
#9650006
0%
