src/memory.v
`default_nettype none

module memory (
    input wire clk,
    input wire rst,
    input wire load_en,
    input wire [2:0] addr, // MSB selects matrix (0: weights, 1: inputs), [1:0] selects element
    input wire [7:0] in_data, // Fixed from reg to wire to match tt_um_tpu.v
    output wire [7:0] weight0, weight1, weight2, weight3, // 2x2 matrix A elements, 1 byte each
    output wire [7:0] input0, input1, input2, input3 // 2x2 matrix B elements, 1 byte each
);

    reg [7:0] sram [0:7]; // 8 locations: 0-3 for weights, 4-7 for inputs
    integer i;

    always @(posedge clk) begin
        if (rst) begin
            for (i = 0; i < 8; i = i + 1) begin
                sram[i] <= 8'b0;
            end
        end else if (load_en) begin
            sram[addr] <= in_data;
        end
    end

    // asynchronous read
    assign weight0 = sram[0];
    assign weight1 = sram[1];
    assign weight2 = sram[2];
    assign weight3 = sram[3];
    assign input0 = sram[4];
    assign input1 = sram[5];
    assign input2 = sram[6];
    assign input3 = sram[7];

endmodule

test/memory/memory_tb.v
`default_nettype none
`timescale 1ns / 1ps

module memory_tb ();

	// Dump the signals to a VCD file. You can view it with gtkwave or surfer.
	initial begin
`ifdef VCD_PATH
		$dumpfile(`VCD_PATH);
`else
		$dumpfile("memory_tb.vcd");
`endif
		$dumpvars(0, memory_tb);
		#1;
	end

	// Inputs
	reg clk;
	reg rst;
	reg load_en;
	reg [2:0] addr;
	reg [7:0] in_data;

	// Outputs
	wire [7:0] weight0, weight1, weight2, weight3;
	wire [7:0] input0, input1, input2, input3;

	// Instantiate the memory module
	memory dut (
		.clk(clk),
		.rst(rst),
		.load_en(load_en),
		.addr(addr),
		.in_data(in_data),
		.weight0(weight0),
		.weight1(weight1),
		.weight2(weight2),
		.weight3(weight3),
		.input0(input0),
		.input1(input1),
		.input2(input2),
		.input3(input3)
	);

endmodule

test/memory/wave/memory_tb_20260512_151433.vcd
$date
	Wed May 13 00:44:34 2026
$end
$version
	Icarus Verilog
$end
$timescale
	1ps
$end
$scope module memory_tb $end
$var wire 8 ! weight3 [7:0] $end
$var wire 8 " weight2 [7:0] $end
$var wire 8 # weight1 [7:0] $end
$var wire 8 $ weight0 [7:0] $end
$var wire 8 % input3 [7:0] $end
$var wire 8 & input2 [7:0] $end
$var wire 8 ' input1 [7:0] $end
$var wire 8 ( input0 [7:0] $end
$var reg 3 ) addr [2:0] $end
$var reg 1 * clk $end
$var reg 8 + in_data [7:0] $end
$var reg 1 , load_en $end
$var reg 1 - rst $end
$scope module dut $end
$var wire 3 . addr [2:0] $end
$var wire 1 * clk $end
$var wire 8 / in_data [7:0] $end
$var wire 8 0 input0 [7:0] $end
$var wire 8 1 input1 [7:0] $end
$var wire 8 2 input2 [7:0] $end
$var wire 8 3 input3 [7:0] $end
$var wire 1 , load_en $end
$var wire 1 - rst $end
$var wire 8 4 weight0 [7:0] $end
$var wire 8 5 weight1 [7:0] $end
$var wire 8 6 weight2 [7:0] $end
$var wire 8 7 weight3 [7:0] $end
$var integer 32 8 i [31:0] $end
$upscope $end
$upscope $end
$enddefinitions $end
$comment Show the parameter values. $end
$dumpall
$end
#0
$dumpvars
b1000 8
b0 7
b0 6
b0 5
b0 4
b0 3
b0 2
b0 1
b0 0
b0 /
b0 .
1-
0,
b0 +
1*
b0 )
b0 (
b0 '
b0 &
b0 %
b0 $
b0 #
b0 "
b0 !
$end
#5000
0*
#10000
0-
b1000 8
1*
#15000
0*
#20000
1*
#20001
1-
#25001
0*
#30001
b1000 8
1*
#35001
0*
#40001
0-
b1000 8
1*
#45001
0*
#50001
b1000 +
b1000 /
1,
1*
#55001
0*
#60001
0,
b1000 $
b1000 4
1*
#65001
0*
#70001
b1001 +
b1001 /
b1 )
b1 .
1,
1*
#75001
0*
#80001
0,
b1001 #
b1001 5
1*
#85001
0*
#90001
b1010 +
b1010 /
b10 )
b10 .
1,
1*
#95001
0*
#100001
0,
b1010 "
b1010 6
1*
#105001
0*
#110001
b1011 +
b1011 /
b11 )
b11 .
1,
1*
#115001
0*
#120001
0,
b1011 !
b1011 7
1*
#125001
0*
#130001
b1100 +
b1100 /
b100 )
b100 .
1,
1*
#135001
0*
#140001
0,
b1100 (
b1100 0
1*
#145001
0*
#150001
b1101 +
b1101 /
b101 )
b101 .
1,
1*
#155001
0*
#160001
0,
b1101 '
b1101 1
1*
#165001
0*
#170001
b1110 +
b1110 /
b110 )
b110 .
1,
1*
#175001
0*
#180001
0,
b1110 &
b1110 2
1*
#185001
0*
#190001
b1111 +
b1111 /
b111 )
b111 .
1,
1*
#195001
0*
#200001
0,
b1111 %
b1111 3
1*
#205001
0*
#210001
1*
#210002
b0 +
b0 /
b0 )
b0 .
1-
#215002
0*
#220002
b0 %
b0 3
b0 &
b0 2
b0 '
b0 1
b0 (
b0 0
b0 !
b0 7
b0 "
b0 6
b0 #
b0 5
b0 $
b0 4
b1000 8
1*
#225002
0*
#230002
0-
b1000 8
1*
#235002
0*
#240002
b11011110 +
b11011110 /
b10 )
b10 .
1*
#245002
0*
#250002
b10111110 +
b10111110 /
1,
1*
#255002
0*
#260002
0,
b10111110 "
b10111110 6
1*
#265002
0*
#270002
1*
#270003
b0 +
b0 /
b0 )
b0 .
1-
#275003
0*
#280003
b0 "
b0 6
b1000 8
1*
#285003
0*
#290003
0-
b1000 8
1*
#295003
0*
#300003
b10001 +
b10001 /
b101 )
b101 .
1,
1*
#305003
0*
#310003
0,
b10001 '
b10001 1
1*
#315003
0*
#320003
b10100101 +
b10100101 /
1,
1*
#325003
0*
#330003
0,
b10100101 '
b10100101 1
1*
#335003
0*
#340003
1*
#340004
b1110111 +
b1110111 /
b0 )
b0 .
1,
1-
#345004
0*
#350004
0,
0-
b0 '
b0 1
b1000 8
1*
#355004
0*
#360004
1*
#360005
b0 +
b0 /
1-
#365005
0*
#370005
b1000 8
1*
#375005
0*
#380005
0-
b1000 8
1*
#385005
0*
#390005
b111011 +
b111011 /
b111 )
b111 .
1,
1*
#395005
0*
#400005
0,
b111011 %
b111011 3
1*
#405005
0*
#410005
b101110 +
b101110 /
b0 )
b0 .
1,
1*
#415005
0*
#420005
0,
b101110 $
b101110 4
1*
#425005
0*
#430005
b101010 +
b101010 /
1,
1*
#435005
0*
#440005
0,
b101010 $
b101010 4
1*
#445005
0*
#450005
b10110101 +
b10110101 /
b1 )
b1 .
1,
1*
#455005
0*
#460005
0,
b10110101 #
b10110101 5
1*
#465005
0*
#470005
b1000 +
b1000 /
b11 )
b11 .
1,
1*
#475005
0*
#480005
0,
b1000 !
b1000 7
1*
#485005
0*
#490005
b0 )
b0 .
1,
1*
#495005
0*
#500005
0,
b1000 $
b1000 4
1*
#505005
0*
#510005
b11110111 +
b11110111 /
b101 )
b101 .
1,
1*
#515005
0*
#520005
0,
b11110111 '
b11110111 1
1*
#525005
0*
#530005
b1001100 +
b1001100 /
b111 )
b111 .
1,
1*
#535005
0*
#540005
0,
b1001100 %
b1001100 3
1*
#545005
0*
#550005
b1011101 +
b1011101 /
b1 )
b1 .
1,
1*
#555005
0*
#560005
0,
b1011101 #
b1011101 5
1*
#565005
0*
#570005
b111 +
b111 /
1,
1*
#575005
0*
#580005
0,
b111 #
b111 5
1*
#585005
0*
#590005
b1111111 +
b1111111 /
b111 )
b111 .
1,
1*
#595005
0*
#600005
0,
b1111111 %
b1111111 3
1*
#605005
0*
#610005
b11101110 +
b11101110 /
b1 )
b1 .
1,
1*
#615005
0*
#620005
0,
b11101110 #
b11101110 5
1*
#625005
0*
#630005
b101101 +
b101101 /
1,
1*
#635005
0*
#640005
0,
b101101 #
b101101 5
1*
#645005
0*
#650005
b10001010 +
b10001010 /
b0 )
b0 .
1,
1*
#655005
0*
#660005
0,
b10001010 $
b10001010 4
1*
#665005
0*
#670005
b10011010 +
b10011010 /
b1 )
b1 .
1,
1*
#675005
0*
#680005
0,
b10011010 #
b10011010 5
1*
#685005
0*
#690005
b10110101 +
b10110101 /
b111 )
b111 .
1,
1*
#695005
0*
#700005
0,
b10110101 %
b10110101 3
1*
#705005
0*
#710005
b1111111 +
b1111111 /
b100 )
b100 .
1,
1*
#715005
0*
#720005
0,
b1111111 (
b1111111 0
1*
#725005
0*
#730005
b11101000 +
b11101000 /
b11 )
b11 .
1,
1*
#735005
0*
#740005
0,
b11101000 !
b11101000 7
1*
#745005
0*
#750005
b100100 +
b100100 /
b0 )
b0 .
1,
1*
#755005
0*
#760005
0,
b100100 $
b100100 4
1*
#765005
0*
#770005
b10101010 +
b10101010 /
1,
1*
#775005
0*
#780005
0,
b10101010 $
b10101010 4
1*
#785005
0*
#790005
b11110010 +
b11110010 /
b10 )
b10 .
1,
1*
#795005
0*
#800005
0,
b11110010 "
b11110010 6
1*
#805005
0*
#810005
b1010101 +
b1010101 /
b110 )
b110 .
1,
1*
#815005
0*
#820005
0,
b1010101 &
b1010101 2
1*
#825005
0*
#830005
b100111 +
b100111 /
b0 )
b0 .
1,
1*
#835005
0*
#840005
0,
b100111 $
b100111 4
1*
#845005
0*
#850005
b1010011 +
b1010011 /
b111 )
b111 .
1,
1*
#855005
0*
#860005
0,
b1010011 %
b1010011 3
1*
#865005
0*
#870005
b1101110 +
b1101110 /
b1 )
b1 .
1,
1*
#875005
0*
#880005
0,
b1101110 #
b1101110 5
1*
#885005
0*
#890005
b1101 +
b1101 /
b10 )
b10 .
1,
1*
#895005
0*
#900005
0,
b1101 "
b1101 6
1*
#905005
0*
#910005
b111000 +
b111000 /
b101 )
b101 .
1,
1*
#915005
0*
#920005
0,
b111000 '
b111000 1
1*
#925005
0*
#930005
b10011100 +
b10011100 /
b10 )
b10 .
1,
1*
#935005
0*
#940005
0,
b10011100 "
b10011100 6
1*
#945005
0*
#950005
b10100 +
b10100 /
b111 )
b111 .
1,
1*
#955005
0*
#960005
0,
b10100 %
b10100 3
1*
#965005
0*
#970005
b10001101 +
b10001101 /
b110 )
b110 .
1,
1*
#975005
0*
#980005
0,
b10001101 &
b10001101 2
1*
#985005
0*
#990005
b1011010 +
b1011010 /
b0 )
b0 .
1,
1*
#995005
0*
#1000005
0,
b1011010 $
b1011010 4
1*
#1005005
0*
#1010005
b1001111 +
b1001111 /
b100 )
b100 .
1,
1*
#1015005
0*
#1020005
0,
b1001111 (
b1001111 0
1*
#1025005
0*
#1030005
1,
1*
#1035005
0*
#1040005
0,
1*
#1045005
0*
#1050005
b10101 +
b10101 /
b111 )
b111 .
1,
1*
#1055005
0*
#1060005
0,
b10101 %
b10101 3
1*
#1065005
0*
#1070005
b10110010 +
b10110010 /
b110 )
b110 .
1,
1*
#1075005
0*
#1080005
0,
b10110010 &
b10110010 2
1*
#1085005
0*
#1090005
b10101110 +
b10101110 /
b111 )
b111 .
1,
1*
#1095005
0*
#1100005
0,
b10101110 %
b10101110 3
1*
#1105005
0*
#1110005
b11110011 +
b11110011 /
1,
1*
#1115005
0*
#1120005
0,
b11110011 %
b11110011 3
1*
#1125005
0*
#1130005
b11110001 +
b11110001 /
b0 )
b0 .
1,
1*
#1135005
0*
#1140005
0,
b11110001 $
b11110001 4
1*
#1145005
0*
#1150005
b11100001 +
b11100001 /
b10 )
b10 .
1,
1*
#1155005
0*
#1160005
0,
b11100001 "
b11100001 6
1*
#1165005
0*
#1170005
b10010111 +
b10010111 /
b111 )
b111 .
1,
1*
#1175005
0*
#1180005
0,
b10010111 %
b10010111 3
1*
#1185005
0*
#1190005
b111111 +
b111111 /
b100 )
b100 .
1,
1*
#1195005
0*
#1200005
0,
b111111 (
b111111 0
1*
#1205005
0*
#1210005
b11010101 +
b11010101 /
b10 )
b10 .
1,
1*
#1215005
0*
#1220005
0,
b11010101 "
b11010101 6
1*
#1225005
0*
#1230005
b111101 +
b111101 /
b110 )
b110 .
1,
1*
#1235005
0*
#1240005
0,
b111101 &
b111101 2
1*
#1245005
0*
#1250005
b11111000 +
b11111000 /
b1 )
b1 .
1,
1*
#1255005
0*
#1260005
0,
b11111000 #
b11111000 5
1*
#1265005
0*
#1270005
b10000010 +
b10000010 /
b110 )
b110 .
1,
1*
#1275005
0*
#1280005
0,
b10000010 &
b10000010 2
1*
#1285005
0*
#1290005
b10110000 +
b10110000 /
b11 )
b11 .
1,
1*
#1295005
0*
#1300005
0,
b10110000 !
b10110000 7
1*
#1305005
0*
#1310005
b1010000 +
b1010000 /
b1 )
b1 .
1,
1*
#1315005
0*
#1320005
0,
b1010000 #
b1010000 5
1*
#1325005
0*
#1330005
b1001111 +
b1001111 /
b100 )
b100 .
1,
1*
#1335005
0*
#1340005
0,
b1001111 (
b1001111 0
1*
#1345005
0*
#1350005
b11100100 +
b11100100 /
b101 )
b101 .
1,
1*
#1355005
0*
#1360005
0,
b11100100 '
b11100100 1
1*
#1365005
0*
#1370005
b101000 +
b101000 /
b1 )
b1 .
1,
1*
#1375005
0*
#1380005
0,
b101000 #
b101000 5
1*
#1385005
0*
#1390005
b1101101 +
b1101101 /
b110 )
b110 .
1,
1*
#1395005
0*
#1400005
0,
b1101101 &
b1101101 2
1*
#1405005
0*
#1410005
b10010010 +
b10010010 /
b0 )
b0 .
1,
1*
#1415005
0*
#1420005
0,
b10010010 $
b10010010 4
1*
#1425005
0*
#1430005
b1110000 +
b1110000 /
1,
1*
#1435005
0*
#1440005
0,
b1110000 $
b1110000 4
1*
#1445005
0*
#1450005
b10100010 +
b10100010 /
b1 )
b1 .
1,
1*
#1455005
0*
#1460005
0,
b10100010 #
b10100010 5
1*
#1465005
0*
#1470005
b11101011 +
b11101011 /
b100 )
b100 .
1,
1*
#1475005
0*
#1480005
0,
b11101011 (
b11101011 0
1*
#1485005
0*
#1490005
b10000011 +
b10000011 /
b1 )
b1 .
1,
1*
#1495005
0*
#1500005
0,
b10000011 #
b10000011 5
1*
#1505005
0*
#1510005
b11011010 +
b11011010 /
1,
1*
#1515005
0*
#1520005
0,
b11011010 #
b11011010 5
1*
#1525005
0*
#1530005
b110011 +
b110011 /
b11 )
b11 .
1,
1*
#1535005
0*
#1540005
0,
b110011 !
b110011 7
1*
#1545005
0*
#1550005
b1100011 +
b1100011 /
b110 )
b110 .
1,
1*
#1555005
0*
#1560005
0,
b1100011 &
b1100011 2
1*
#1565005
0*
#1570005
b1111000 +
b1111000 /
b111 )
b111 .
1,
1*
#1575005
0*
#1580005
0,
b1111000 %
b1111000 3
1*
#1585005
0*
#1590005
b1101001 +
b1101001 /
b101 )
b101 .
1,
1*
#1595005
0*
#1600005
0,
b1101001 '
b1101001 1
1*
#1605005
0*
#1610005
b1011001 +
b1011001 /
b110 )
b110 .
1,
1*
#1615005
0*
#1620005
0,
b1011001 &
b1011001 2
1*
#1625005
0*
#1630005
b10011010 +
b10011010 /
b11 )
b11 .
1,
1*
#1635005
0*
#1640005
0,
b10011010 !
b10011010 7
1*
#1645005
0*
#1650005
b10110100 +
b10110100 /
b0 )
b0 .
1,
1*
#1655005
0*
#1660005
0,
b10110100 $
b10110100 4
1*
